[{"name":"Abidjan","category":null,"lat":5.336317999999999,"lng":-4.027750999999999,"project_id":"2","cris_id":"280342"},{"name":"Abidjan","category":null,"lat":5.336317999999999,"lng":-4.027750999999999,"project_id":"5","cris_id":"21309"},{"name":"Abidjan","category":null,"lat":5.336317999999999,"lng":-4.027750999999999,"project_id":"6","cris_id":"238695"},{"name":"Abidjan","category":null,"lat":5.336317999999999,"lng":-4.027750999999999,"project_id":"7","cris_id":"23813"},{"name":"Abidjan","category":null,"lat":5.336317999999999,"lng":-4.027750999999999,"project_id":"8","cris_id":"21384"},{"name":"Abidjan","category":null,"lat":5.336317999999999,"lng":-4.027750999999999,"project_id":"12","cris_id":"206174"},{"name":"région de la vallée du Bandama","category":null,"lat":8.278978,"lng":-4.893562699999999,"project_id":"13","cris_id":"239030"}]